LICENSE
README.md
setup.py
obsidian_plugin_stats/__init__.py
obsidian_plugin_stats/main.py
obsidian_plugin_stats.egg-info/PKG-INFO
obsidian_plugin_stats.egg-info/SOURCES.txt
obsidian_plugin_stats.egg-info/dependency_links.txt
obsidian_plugin_stats.egg-info/entry_points.txt
obsidian_plugin_stats.egg-info/top_level.txt