Metadata-Version: 2.1
Name: obsidian-plugin-stats
Version: 1.0.0
Summary: Fetch and maintain download statistics for an Obsidian Plugin
Home-page: https://github.com/talwrii/obsidian-plugin-stats
Author: @readwithai
Author-email: talwrii@gmail.com
License: BSD
License-File: LICENSE
